{
  "batch_id": "B-023",
  "rf_pass": "RF-13",
  "rf_name": "Escalation Patterns",
  "date_range": {
    "start": "2025-02-21",
    "end": "2025-03-11"
  },
  "row_range": {
    "start": 8523,
    "end": 8916
  },
  "message_count": 514,
  "phase": "A",
  "analysis_date": "2026-04-28",
  "arc_state_at_batch_start": {
    "ARC-RF13-001": "ACTIVE",
    "ARC-RF13-002": "ACTIVE",
    "ARC-RF13-003": "ACTIVE"
  },
  "arc_signals_cumulative": 13,
  "calibration_addenda_active": [
    "RF13-ADD-001",
    "RF13-ADD-002",
    "RF13-ADD-003",
    "RF13-ADD-004",
    "RF13-ADD-005"
  ],
  "batch_summary": {
    "primary_flags": 1,
    "peripheral_flags": 0,
    "hostile_episodes": 1,
    "note": "One hostile episode: EP-1038 Mar 10 2025 (39 msgs, FLOOD). Post-Feb-mega-cluster. Single episode; Sev-1."
  },
  "primary_flags": [
    {
      "flag_id": "RF13-B023-001",
      "episode_id": "EP-1038",
      "date": "2025-03-10",
      "message_count": 39,
      "phase": "A",
      "flooding_detected": true,
      "severity": 1,
      "escalation_shape": "spike \u2014 single hostile episode post-Feb cluster",
      "primary_escalator": "received",
      "delta_profile": {
        "sent_direction": "measured response",
        "received_direction": "hostile initiation; flooding; 39-msg exchange",
        "net_escalation": "moderate Sev-1",
        "de_escalation_resistance": "Eli responds briefly; exchange ends after single episode"
      },
      "cycle_classification": "CYC-002 content-correlated \u2014 post-mega-cluster re-escalation",
      "arc_associations": [
        "ARC-RF13-001",
        "ARC-RF13-002",
        "ARC-RF13-003"
      ],
      "arc_signal_number": 14,
      "cross_rf_note": "B-023 post-Feb 2025 cluster period. RF-04 signals active."
    }
  ],
  "peripheral_flags": [],
  "arc_updates": []
}